laiye_dataservice/__init__.py
laiye_dataservice/dataservice.py
laiye_dataservice/do.py
laiye_dataservice/enums.py
laiye_dataservice/errors.py
laiye_dataservice/jwt/__init__.py
laiye_dataservice/jwt/__main__.py
laiye_dataservice/jwt/algorithms.py
laiye_dataservice/jwt/api_jws.py
laiye_dataservice/jwt/api_jwt.py
laiye_dataservice/jwt/compat.py
laiye_dataservice/jwt/exceptions.py
laiye_dataservice/jwt/help.py
laiye_dataservice/jwt/utils.py
tests/__init__.py
tests/local_data.py
tests/test_flow_01.py
tests/test_flow_02_jwt_token.py
tests/test_flow_03_BI.py
tests/test_flow_10_exception_test.py
laiye_dataservice_sdk-1.6.3.2.dist-info/METADATA
laiye_dataservice_sdk-1.6.3.2.dist-info/WHEEL
laiye_dataservice_sdk-1.6.3.2.dist-info/top_level.txt
laiye_dataservice_sdk-1.6.3.2.dist-info/RECORD
