Metadata-Version: 2.1
Name: laiye-dataservice-sdk
Version: 1.6.3.2
Summary: UNKNOWN
Home-page: https://git.laiye.com/laiye-dataservice/laiye-dataservice-sdk
Author: kangyongsheng
Author-email: kangyongsheng@laiye.com
License: UNKNOWN
Platform: UNKNOWN
Classifier: Intended Audience :: Developers
Classifier: License :: OSI Approved :: Apache Software License
Classifier: Programming Language :: Python
Classifier: Programming Language :: Python :: 3.6
Classifier: Programming Language :: Python :: 3.7
Classifier: Programming Language :: Python :: 3.8
Classifier: Topic :: Software Development
Requires-Python: >=3.6
Requires-Dist: requests
